tweepi
