Metadata-Version: 1.1
Name: tweepi
Version: 0.2.2
Summary: Stateful Twitter API client
Home-page: https://github.com/jacobgreenleaf/twitter-api
Author: Jacob Greenleaf
Author-email: jacob@jacobgreenleaf.com
License: MIT
Platform: UNKNOWN
Classifier: Development Status :: 4 - Beta
Classifier: Intended Audience :: Developers
Classifier: License :: OSI Approved :: MIT License
Classifier: Programming Language :: Python :: 2.7
Classifier: Programming Language :: Python :: 3
Classifier: Programming Language :: Python :: 3.2
Classifier: Programming Language :: Python :: 3.3
Classifier: Programming Language :: Python :: 3.4
